yccloudpickle-0.2.2.3.dist-info/top_level.txt
yccloudpickle-0.2.2.3.dist-info/RECORD
yccloudpickle-0.2.2.3.dist-info/DESCRIPTION.rst
yccloudpickle-0.2.2.3.dist-info/metadata.json
yccloudpickle-0.2.2.3.dist-info/METADATA
yccloudpickle-0.2.2.3.dist-info/WHEEL
yccloudpickle/yccloudpickle.py
yccloudpickle/__init__.py
